Metadata-Version: 2.1
Name: somepackages
Version: 0.1.3
Summary: It is just utils
Home-page: https://github.com/javatechy/dokr
Author: gelleson
Author-email: go.gelleson@gmail.com
License: UNKNOWN
Platform: UNKNOWN
Classifier: Programming Language :: Python :: 3
Classifier: License :: OSI Approved :: MIT License
Classifier: Operating System :: OS Independent
